rest_helper/__init__.py
rest_helper/rest_helper.py
rest_helper-0.0.3.dist-info/LICENSE
rest_helper-0.0.3.dist-info/METADATA
rest_helper-0.0.3.dist-info/WHEEL
rest_helper-0.0.3.dist-info/top_level.txt
rest_helper-0.0.3.dist-info/RECORD
