Metadata-Version: 2.1
Name: rest-helper
Version: 0.0.3
Summary: Utility tool used for parsing specific .ini files
Author: Norbert Gocze
Author-email: gnorbi951@gmail.com
Keywords: rest_helper
Requires-Python: >=3.6
License-File: LICENSE
Requires-Dist: docopt
